landfill.py
landfill-0.2.0.dist-info/DESCRIPTION.rst
landfill-0.2.0.dist-info/METADATA
landfill-0.2.0.dist-info/metadata.json
landfill-0.2.0.dist-info/RECORD
landfill-0.2.0.dist-info/top_level.txt
landfill-0.2.0.dist-info/WHEEL
