Metadata-Version: 2.0
Name: landfill
Version: 0.2.0
Summary: Migration management for peewee orm
Home-page: https://github.com/Checksum/landfill
Author: Srinath
Author-email: srinath@iambot.net
License: MIT
Keywords: peewee,migrations,orm
Platform: UNKNOWN
Classifier: Development Status :: 3 - Alpha
Classifier: Programming Language :: Python
Classifier: Topic :: Utilities
Classifier: Topic :: Software Development :: Libraries :: Python Modules
Classifier: License :: OSI Approved :: MIT License
Requires-Dist: peewee
Requires-Dist: termcolor
